amancal/__init__.py
amancal/calculator.py
amancal-0.1.0.dist-info/METADATA
amancal-0.1.0.dist-info/WHEEL
amancal-0.1.0.dist-info/entry_points.txt
amancal-0.1.0.dist-info/top_level.txt
amancal-0.1.0.dist-info/RECORD
